anim/__init__.py
anim/colormap.py
anim/information.py
anim/time.py
anim/window.py
anim/plane/__init__.py
anim/plane/composites.py
anim/plane/items.py
anim/plane/panel.py
anim/style/dark.css
anim/style/light.css
anim/style/white.css
lib_anim-0.0.8.dist-info/licenses/LICENSE
lib_anim-0.0.8.dist-info/METADATA
lib_anim-0.0.8.dist-info/WHEEL
lib_anim-0.0.8.dist-info/top_level.txt
lib_anim-0.0.8.dist-info/RECORD
