Metadata-Version: 2.4
Name: lib-anim
Version: 0.0.8
Summary: Beautifully simple animations
Author: Raphaël Candelier
Author-email: raphael.candelier@sorbonne-universite.fr
License: GNU GPL v3
Keywords: conversion
Classifier: Development Status :: 4 - Beta
Classifier: Intended Audience :: Science/Research
Classifier: Intended Audience :: Education
Classifier: License :: OSI Approved :: GNU General Public License v3 (GPLv3)
Classifier: Programming Language :: Python :: 3
Classifier: Topic :: Scientific/Engineering :: Visualization
License-File: LICENSE
Requires-Dist: numpy
Requires-Dist: matplotlib
Requires-Dist: pyqt6
Requires-Dist: imageio[ffmpeg]
Dynamic: author
Dynamic: author-email
Dynamic: classifier
Dynamic: description
Dynamic: keywords
Dynamic: license
Dynamic: license-file
Dynamic: requires-dist
Dynamic: summary
